tartes/__init__.py
tartes/impurities.py
tartes/refice.py
tartes/refractive_index.py
tartes/tartes.py
tartes-2.0.3.dist-info/COPYING.txt
tartes-2.0.3.dist-info/METADATA
tartes-2.0.3.dist-info/WHEEL
tartes-2.0.3.dist-info/top_level.txt
tartes-2.0.3.dist-info/RECORD
