Metadata-Version: 2.2
Name: tartes
Version: 2.0.3
Summary: Two-stream radiative transfer in snow model
Home-page: http://gp.snow-physics.science/tartes/
Author: Quentin Libois, Ghislain Picard
Author-email: quentin.libois@meteo.fr, ghislain.picard@univ-grenoble-alpes.fr
Keywords: radiative transfer,model,snow,optics
Classifier: Programming Language :: Python
Classifier: Programming Language :: Python :: 2
Classifier: Programming Language :: Python :: 3
Classifier: Development Status :: 5 - Production/Stable
Classifier: Environment :: Other Environment
Classifier: Intended Audience :: Science/Research
Classifier: License :: OSI Approved :: GNU Library or Lesser General Public License (LGPL)
Classifier: Operating System :: OS Independent
Classifier: Topic :: Scientific/Engineering :: Atmospheric Science
License-File: COPYING.txt
Dynamic: author
Dynamic: author-email
Dynamic: classifier
Dynamic: description
Dynamic: home-page
Dynamic: keywords
Dynamic: summary
